pywebagent/__init__.py
pywebagent/agent.py
pywebagent/env/__init__.py
pywebagent/env/actions.py
pywebagent/env/browser.py
pywebagent/js/mark_borders.js
pywebagent/js/override_file_chooser.js
pywebagent/js/remove_mark_borders.js
pywebagent-0.1.dist-info/LICENSE
pywebagent-0.1.dist-info/METADATA
pywebagent-0.1.dist-info/WHEEL
pywebagent-0.1.dist-info/top_level.txt
pywebagent-0.1.dist-info/RECORD
