Metadata-Version: 2.1
Name: pywebagent
Version: 0.1
Summary: An experimental AI web agent
Author-email: Ori Kabeli <ori.kabeli@gmail.com>, Maxim Kogan <maximkgn@gmail.com>
License: MIT License
Project-URL: Homepage, https://github.com/pywebagent/pywebagent
Keywords: Web agent,Web automation,Web testing,Web action agent
Classifier: Development Status :: 3 - Alpha
Classifier: Topic :: Scientific/Engineering :: Artificial Intelligence
Classifier: Environment :: Console
Classifier: Programming Language :: Python :: 3.10
Requires-Python: >=3.10
License-File: LICENSE
Requires-Dist: langchain
Requires-Dist: openai
Requires-Dist: setuptools
Requires-Dist: python-dotenv
Requires-Dist: argparse
Requires-Dist: playwright
